{
  "name": "超声波传感器HC-SR04",
  "id": "ctm-超声波传感器hcsr04-120000",
  "description": "超声波测距传感器。工作电压5V，工作电流15mA，测量范围2cm-400cm，测量精度3mm，探测角度15°。",
  "category": "sensor",
  "pins": {
    "side1": [
      {
        "pinName": "VCC",
        "type": "power",
        "order": 1
      },
      {
        "pinName": "Trig",
        "type": "digital_io",
        "order": 2
      },
      {
        "pinName": "Echo",
        "type": "digital_io",
        "order": 3
      },
      {
        "pinName": "GND",
        "type": "ground",
        "order": 4
      }
    ],
    "side2": [],
    "side3": [],
    "side4": []
  },
  "dimensions": {
    "width": 190,
    "height": 35
  }
}